{
  "mouth-happy": {
    "url": "images/mouthHappyAnimation.png",
    "frames": 4,
    "styles": {
      "top": "36%",
      "left": "23%",
      "height": "21%",
      "aspect-ratio": "1.1/1"
    }
  },
  "mouth-distressed": {
    "url": "images/mouthDistressedAnimation.png",
    "frames": 5,
    "styles": {
      "top": "36%",
      "left": "23%",
      "height": "19%",
      "aspect-ratio": "1.1/1"
    }
  },
  "mouth-flirty": {
    "url": "images/mouthFlirtyAnimation.png",
    "frames": 4,
    "styles": {
      "top": "36%",
      "left": "23%",
      "height": "19%",
      "aspect-ratio": "1.1/1"
    }
  },
  "sweat": {
    "url": "images/mouthAnimation0 copy.png",
    "frames": 1,
    "styles": {
      "top": "24%",
      "left": "15%",
      "height": "26%",
      "aspect-ratio": "1.1/1"
    }
  },
  "default": {
    "url": "images/mouthHappyAnimation.png",
    "frames": 4,
    "styles": {
      "top": "36%",
      "left": "23%",
      "height": "21%",
      "aspect-ratio": "1.1/1"
    }
  }
}
